arcade_k8s/__init__.py
arcade_k8s/tools/__init__.py
arcade_k8s/tools/nodes.py
arcade_k8s/tools/pods.py
arcade_k8s-0.1.1.dist-info/METADATA
arcade_k8s-0.1.1.dist-info/WHEEL
arcade_k8s-0.1.1.dist-info/entry_points.txt
arcade_k8s-0.1.1.dist-info/RECORD
